haplo/__init__.py
haplo/main.py
haplo/drivers/chromedriver_linux
haplo/drivers/chromedriver_mac
haplo/drivers/chromedriver_win.exe
haplostat-0.6.0.dist-info/METADATA
haplostat-0.6.0.dist-info/WHEEL
haplostat-0.6.0.dist-info/entry_points.txt
haplostat-0.6.0.dist-info/top_level.txt
haplostat-0.6.0.dist-info/RECORD
